start.v
// Variant 1 : y = a ^ 2 + b ^ (1/3)
// Restrictions: 1 summation, 2 multiplications
`timescale 1ns/1ps
module mult(
    input clk,
    input rst,
    input start,
    input [7:0] a_in,
    input [7:0] b_in,
    output reg [15:0] f_out,
    output reg busy_o
);
    localparam IDLE = 1'b0;
    localparam WORK = 1'b1;
    
    reg state;
    reg [7:0] sum;
    reg [7:0] counter;
    
    reg [7:0] mult1_a_in, mult1_b_in;
    always @(posedge clk) begin
        if (rst) begin
            state <= IDLE;
            sum <= 8'd0;
            counter <= 8'd0;
            f_out <= 8'd0;
            busy_o <= 1'b0;
            mult1_a_in <= 0;
            mult1_b_in <= 0;
        end else begin
            case (state)
                IDLE: begin
                    if (start) begin
                        busy_o <= 1'b1;
                        sum <= 8'd0;
                        f_out <= 8'd0;
                        counter <= 8'd0;
                        mult1_a_in <= a_in;
                        mult1_b_in <= b_in;
                        state <= WORK;
                    end
                end
                WORK: begin
                    counter <= counter + 1;
                    if (counter < b_in) begin
                        sum <= sum + a_in;
                    end else begin
                        f_out <= sum;
                        busy_o <= 1'b0;
                        state <= IDLE;
                    end
                end
            endcase
        end
    end
endmodule

module cubicroot(
    input clk,
    input rst,
    input start,
    input [7:0] x_in,
    output reg [7:0] y_out,
    output reg busy_o
);
    // State encoding
    localparam IDLE          = 4'd0;
    localparam SHIFT_Y       = 4'd1;
    localparam COMPUTE_B1_MULT_OFF = 4'd2;
    localparam COMPUTE_B2    = 4'd3;
    localparam COMPUTE_B2_MULT_OFF    = 4'd4;
    localparam COMPUTE_B3    = 4'd5;
    localparam COMPARE      = 4'd6;
    localparam DECREMENT_S        = 4'd7;
    localparam COMPUTE_B1_MULT_OFF_WAIT = 4'd8;
    localparam COMPUTE_B2_MULT_OFF_WAIT = 4'd9;
    localparam SHIFT_Y_END = 4'd10;

    reg [7:0] x;
    reg [7:0] y;
    reg [8:0] b;
    reg [4:0] s;
    reg [3:0] state;
    reg [15:0] mult_reg;

    reg mult1_start;
    wire mult1_busy;
    wire [15:0] mult1_f_out;
    reg [7:0] mult1_a_in, mult1_b_in;
    

    mult mult1_inst (
        .clk(clk),
        .rst(rst),
        .start(mult1_start),
        .a_in(mult1_a_in),
        .b_in(mult1_b_in),
        .f_out(mult1_f_out),
        .busy_o(mult1_busy)
    );


    always @(posedge clk) begin
        if (rst) begin
            state <= IDLE;
            x <= 0;
            y <= 0;
            s <= 0;
            b <= 0;
            busy_o <= 0;
            y_out <= 0;
            mult1_start <= 0;
            mult_reg <= 0;
            
        end else begin
            case (state)
                IDLE: begin
                    if (start) begin
                        x <= x_in;
                        y <= 0;
                        s <= 5'd6;
                        state <= SHIFT_Y;
                        mult_reg <= 0;
                        b <= 0;
                        mult1_a_in <= 0;
                        mult1_b_in <= 0;
                        mult1_start <= 0;
                        busy_o <= 1'b1;
                    end
                end
                SHIFT_Y: begin
                    $display();
                    $display("-=-=-=-=-=-=-=-=-");
                    $write(" s:", s);
                    $write(" y:%d", y);
                    y <= y << 1;
                    state <= SHIFT_Y_END;
                end
                SHIFT_Y_END: begin
                    
                    mult1_a_in <= y + 1;
                    mult1_b_in <= y;
                    mult1_start <= 1;
                    state <= COMPUTE_B1_MULT_OFF;
                end
                COMPUTE_B1_MULT_OFF: begin
                    mult1_start <= 0;
                    mult_reg <= 0;
                    state <= COMPUTE_B1_MULT_OFF_WAIT;
                end
                COMPUTE_B1_MULT_OFF_WAIT: begin
                    if (!mult1_busy) begin
                        mult_reg <= mult1_f_out;
                        state <= COMPUTE_B2;
                    end
                end
                COMPUTE_B2: begin
                    $write(" mult_reg:", mult_reg);
                    mult1_a_in <= 0;
                        mult1_b_in <= 0;
                        mult1_start <= 0;
                    mult1_a_in <= 3;
                    mult1_b_in <= mult_reg;
                    mult1_start <= 1;
                    state <= COMPUTE_B2_MULT_OFF;
                end
                COMPUTE_B2_MULT_OFF: begin
                    mult1_start <= 0;
                    mult_reg <= 0;
                    state <= COMPUTE_B2_MULT_OFF_WAIT;
                end
                COMPUTE_B2_MULT_OFF_WAIT: begin
                    if (!mult1_busy) begin
                        mult_reg <= mult1_f_out;
                        state <= COMPUTE_B3;
                    end
                end
                COMPUTE_B3: begin
                    b <= (mult_reg + 1) << s;
                    mult_reg <= 0;
                    state <= COMPARE;
                end
                COMPARE: begin
                    $write(" b<<%b:", b);
                    if (x >= b) begin
                        $write(" x>=b");
                        x <= x - b;
                        y <= y + 1;
                        state <= DECREMENT_S;
                    end else begin
                        state <= DECREMENT_S;
                    end
                end 
                DECREMENT_S: begin
                    if (s >= 3) begin
                        s <= s - 3;
                        state <= SHIFT_Y;
                    end else begin
                        y_out <= y;
                        state <= IDLE;
                        busy_o <= 0;
                    end
                end
                default: state <= IDLE;
            endcase
        end
    end
endmodule

module clock_gen(
    output reg clk
);
    initial begin
        clk <= 1'b1;
        forever #1 clk <= ~clk;
    end
endmodule

module cubicroot_test;
    wire clk;
    reg rst;
    reg start;
    reg [7:0] x_in;
    wire [7:0] y_out;
    wire busy;

    assign ready = ~busy;

    cubicroot cubicroot_inst (
        .clk(clk),
        .rst(rst),
        .start(start),
        .x_in(x_in),
        .y_out(y_out),
        .busy_o(busy)
    );

    clock_gen cg_inst (
        .clk(clk)
    );

    integer i;
    reg [7:0] cube;

    initial begin
        $dumpfile("test.vcd");
        $dumpvars(0, cubicroot_test);
        rst <= 1;
        start <= 0;
        x_in <= 8'd0;

        #40 rst <= 0;
        $display("Cubic root test:");
        
        for (i = 0; i <= 10; i = i + 1) begin
            cube = i * i * i;
            // #10;
            
            x_in <= cube;
            start <= 1;
            #2; start <= 0;

            wait (ready);
            $display("cubicroot(%b) = %d (expected %d)", cube, y_out, i);
            #100;
        end
        for (i = 0; i <= 6; i = i + 1) begin
            cube = i * i * i;
            // #10;
            
            x_in <= cube;
            start <= 1;
            #2; start <= 0;

            wait (ready);
            $display("cubicroot(%b) = %d (expected %d)", cube, y_out, i);
            #100;
        end
        $finish;
    end
endmodule

// module mult_test;
//     wire clk;
//     reg rst;
//     reg start;
//     reg [7:0] a_in;
//     reg [7:0] b_in;
//     wire [15:0] f_out;
//     wire busy_o;

//     mult mult_inst (
//         .clk(clk),
//         .rst(rst),
//         .start(start),
//         .a_in(a_in),
//         .b_in(b_in),
//         .f_out(f_out),
//         .busy_o(busy_o)
//     );

//     clock_gen cg_inst (
//         .clk(clk)
//     );

//     integer i, j;

//     initial begin
//         rst = 1;
//         start = 0;
//         a_in = 8'd0;
//         b_in = 8'd0;

//         #20 rst = 0;
//         $display("Multiplier test:");

//         for (i = 0; i <= 12; i = i + 1) begin
//             for (j = 0; j <= 12; j = j + 1) begin
//                 #10;
//                 a_in = i;
//                 b_in = j;
//                 start = 1;
//                 #2 start = 0;

//                 wait (!busy_o);
//                 $display("%d * %d = %d", i, j, f_out);
//             end
//         end

//         $display("-=-=-=-=-=-=-=-=-=");
//         $finish;
//     end
// endmodule

test.vcd
$date
	Fri Nov 29 01:43:46 2024
$end
$version
	Icarus Verilog
$end
$timescale
	1ps
$end
$scope module cubicroot_test $end
$var wire 1 ! ready $end
$var wire 8 " y_out [7:0] $end
$var wire 1 # clk $end
$var wire 1 $ busy $end
$var reg 8 % cube [7:0] $end
$var reg 1 & rst $end
$var reg 1 ' start $end
$var reg 8 ( x_in [7:0] $end
$var integer 32 ) i [31:0] $end
$scope module cg_inst $end
$var reg 1 # clk $end
$upscope $end
$scope module cubicroot_inst $end
$var wire 1 # clk $end
$var wire 1 & rst $end
$var wire 1 ' start $end
$var wire 8 * x_in [7:0] $end
$var wire 16 + mult1_f_out [15:0] $end
$var wire 1 , mult1_busy $end
$var parameter 4 - COMPARE $end
$var parameter 4 . COMPUTE_B1_MULT_OFF $end
$var parameter 4 / COMPUTE_B1_MULT_OFF_WAIT $end
$var parameter 4 0 COMPUTE_B2 $end
$var parameter 4 1 COMPUTE_B2_MULT_OFF $end
$var parameter 4 2 COMPUTE_B2_MULT_OFF_WAIT $end
$var parameter 4 3 COMPUTE_B3 $end
$var parameter 4 4 DECREMENT_S $end
$var parameter 4 5 IDLE $end
$var parameter 4 6 SHIFT_Y $end
$var parameter 4 7 SHIFT_Y_END $end
$var reg 9 8 b [8:0] $end
$var reg 1 $ busy_o $end
$var reg 8 9 mult1_a_in [7:0] $end
$var reg 8 : mult1_b_in [7:0] $end
$var reg 1 ; mult1_start $end
$var reg 16 < mult_reg [15:0] $end
$var reg 5 = s [4:0] $end
$var reg 4 > state [3:0] $end
$var reg 8 ? x [7:0] $end
$var reg 8 @ y [7:0] $end
$var reg 8 A y_out [7:0] $end
$scope module mult1_inst $end
$var wire 8 B a_in [7:0] $end
$var wire 8 C b_in [7:0] $end
$var wire 1 # clk $end
$var wire 1 & rst $end
$var wire 1 ; start $end
$var parameter 1 D IDLE $end
$var parameter 1 E WORK $end
$var reg 1 , busy_o $end
$var reg 8 F counter [7:0] $end
$var reg 16 G f_out [15:0] $end
$var reg 8 H mult1_a_in [7:0] $end
$var reg 8 I mult1_b_in [7:0] $end
$var reg 1 J state $end
$var reg 8 K sum [7:0] $end
$upscope $end
$upscope $end
$upscope $end
$enddefinitions $end
$comment Show the parameter values. $end
$dumpall
1E
0D
b1010 7
b1 6
b0 5
b111 4
b101 3
b1001 2
b100 1
b11 0
b1000 /
b10 .
b110 -
$end
#0
$dumpvars
b0 K
0J
b0 I
b0 H
b0 G
b0 F
bx C
bx B
b0 A
b0 @
b0 ?
b0 >
b0 =
b0 <
0;
bx :
bx 9
b0 8
0,
b0 +
b0 *
bx )
b0 (
0'
1&
bx %
0$
1#
b0 "
1!
$end
#1000
0#
#2000
1#
#3000
0#
#4000
1#
#5000
0#
#6000
1#
#7000
0#
#8000
1#
#9000
0#
#10000
1#
#11000
0#
#12000
1#
#13000
0#
#14000
1#
#15000
0#
#16000
1#
#17000
0#
#18000
1#
#19000
0#
#20000
1#
#21000
0#
#22000
1#
#23000
0#
#24000
1#
#25000
0#
#26000
1#
#27000
0#
#28000
1#
#29000
0#
#30000
1#
#31000
0#
#32000
1#
#33000
0#
#34000
1#
#35000
0#
#36000
1#
#37000
0#
#38000
1#
#39000
0#
#40000
0!
1$
b0 :
b0 C
b0 9
b0 B
b1 >
b110 =
1#
1'
0&
b0 %
b0 )
#41000
0#
#42000
b1010 >
1#
0'
#43000
0#
#44000
b10 >
1;
b1 9
b1 B
1#
#45000
0#
#46000
b1000 >
0;
1J
b1 H
1,
1#
#47000
0#
#48000
0J
0,
b1 F
1#
#49000
0#
#50000
b11 >
1#
#51000
0#
#52000
b100 >
1;
b11 9
b11 B
1#
#53000
0#
#54000
b1001 >
0;
1J
b11 H
b0 F
1,
1#
#55000
0#
#56000
0J
0,
b1 F
1#
#57000
0#
#58000
b101 >
1#
#59000
0#
#60000
b110 >
b1000000 8
1#
#61000
0#
#62000
b111 >
1#
#63000
0#
#64000
b1 >
b11 =
1#
#65000
0#
#66000
b1010 >
1#
#67000
0#
#68000
b10 >
1;
b1 9
b1 B
1#
#69000
0#
#70000
b1000 >
0;
1J
b1 H
b0 F
1,
1#
#71000
0#
#72000
0J
0,
b1 F
1#
#73000
0#
#74000
b11 >
1#
#75000
0#
#76000
b100 >
1;
b11 9
b11 B
1#
#77000
0#
#78000
b1001 >
0;
1J
b11 H
b0 F
1,
1#
#79000
0#
#80000
0J
0,
b1 F
1#
#81000
0#
#82000
b101 >
1#
#83000
0#
#84000
b110 >
b1000 8
1#
#85000
0#
#86000
b111 >
1#
#87000
0#
#88000
b1 >
b0 =
1#
#89000
0#
#90000
b1010 >
1#
#91000
0#
#92000
b10 >
1;
b1 9
b1 B
1#
#93000
0#
#94000
b1000 >
0;
1J
b1 H
b0 F
1,
1#
#95000
0#
#96000
0J
0,
b1 F
1#
#97000
0#
#98000
b11 >
1#
#99000
0#
#100000
b100 >
1;
b11 9
b11 B
1#
#101000
0#
#102000
b1001 >
0;
1J
b11 H
b0 F
1,
1#
#103000
0#
#104000
0J
0,
b1 F
1#
#105000
0#
#106000
b101 >
1#
#107000
0#
#108000
b110 >
b1 8
1#
#109000
0#
#110000
b111 >
1#
#111000
0#
#112000
1!
0$
b0 >
1#
